setup.py
qython/__init__.py
qython.egg-info/PKG-INFO
qython.egg-info/SOURCES.txt
qython.egg-info/dependency_links.txt
qython.egg-info/top_level.txt
qython/datetime/__init__.py
test/test_datetime.py