Metadata-Version: 1.0
Name: qython
Version: 0.0.2
Summary: A missing library for python.
Home-page: https://github.com/vamf12/qython
Author: UNKNOWN
Author-email: UNKNOWN
License: BSD
Platform: UNKNOWN
